docs/Makefile
docs/make.bat
docs/source/apple_silicon_x86_setup.rst
docs/source/conf.py
docs/source/dual_autodiff.rst
docs/source/index.rst
docs/source/modules.rst
docs/source/tutorial.rst
dual_autodiff/__init__.py
dual_autodiff/base.py
dual_autodiff/dual.py
dual_autodiff/functions.py
dual_autodiff/version.py
dual_autodiff_x/MANIFEST.in
dual_autodiff_x/README.md
dual_autodiff_x/pyproject.toml
dual_autodiff_x/setup.py
dual_autodiff_x/dual_autodiff_x/__init__.py
dual_autodiff_x/dual_autodiff_x/base.pyx
dual_autodiff_x/dual_autodiff_x/dual.pyx
dual_autodiff_x/dual_autodiff_x/functions.pyx
dual_autodiff_x/dual_autodiff_x/version.pyx
dual_autodiff_x/wheel_contents/310_wheel_contents/dual_autodiff_x/__init__.py
dual_autodiff_x/wheel_contents/311_wheel_contents/dual_autodiff_x/__init__.py
dual_autodiff_x/wheelhouse/rsr45_dual_autodiff_x-0.1.16-cp310-cp310-linux_x86_64.whl
dual_autodiff_x/wheelhouse/rsr45_dual_autodiff_x-0.1.16-cp310-cp310-manylinux_2_17_x86_64.manylinux2014_x86_64.whl
dual_autodiff_x/wheelhouse/rsr45_dual_autodiff_x-0.1.16-cp311-cp311-linux_x86_64.whl
dual_autodiff_x/wheelhouse/rsr45_dual_autodiff_x-0.1.16-cp311-cp311-manylinux_2_17_x86_64.manylinux2014_x86_64.whl
report/cam_logo_bw.png
report/convergence_derivative.png
report/performance_comparison.png
report/references.bib
report/report.pdf
report/report.tex
tests/test_base.py
tests/test_dual.py
tests/test_functions.py
dual_autodiff_x/wheel_contents/310_wheel_contents/rsr45_dual_autodiff_x-0.1.16.dist-info/METADATA
dual_autodiff_x/wheel_contents/310_wheel_contents/rsr45_dual_autodiff_x-0.1.16.dist-info/RECORD
dual_autodiff_x/wheel_contents/310_wheel_contents/rsr45_dual_autodiff_x-0.1.16.dist-info/WHEEL
dual_autodiff_x/wheel_contents/310_wheel_contents/rsr45_dual_autodiff_x-0.1.16.dist-info/top_level.txt
dual_autodiff_x/wheel_contents/311_wheel_contents/rsr45_dual_autodiff_x-0.1.16.dist-info/METADATA
dual_autodiff_x/wheel_contents/311_wheel_contents/rsr45_dual_autodiff_x-0.1.16.dist-info/RECORD
dual_autodiff_x/wheel_contents/311_wheel_contents/rsr45_dual_autodiff_x-0.1.16.dist-info/WHEEL
dual_autodiff_x/wheel_contents/311_wheel_contents/rsr45_dual_autodiff_x-0.1.16.dist-info/top_level.txt
rsr45_dual_autodiff-0.0.post46.dist-info/LICENCE
rsr45_dual_autodiff-0.0.post46.dist-info/METADATA
rsr45_dual_autodiff-0.0.post46.dist-info/WHEEL
rsr45_dual_autodiff-0.0.post46.dist-info/entry_points.txt
rsr45_dual_autodiff-0.0.post46.dist-info/top_level.txt
rsr45_dual_autodiff-0.0.post46.dist-info/RECORD
